jaraco/text/Lorem ipsum.txt
jaraco/text/__init__.py
jaraco/text/layouts.py
jaraco/text/show-newlines.py
jaraco/text/strip-prefix.py
jaraco/text/to-dvorak.py
jaraco/text/to-qwerty.py
jaraco.text-4.0.0.dist-info/LICENSE
jaraco.text-4.0.0.dist-info/METADATA
jaraco.text-4.0.0.dist-info/WHEEL
jaraco.text-4.0.0.dist-info/top_level.txt
jaraco.text-4.0.0.dist-info/RECORD
