Metadata-Version: 2.1
Name: jaraco.text
Version: 4.0.0
Summary: Module for text manipulation
Author-email: "Jason R. Coombs" <jaraco@jaraco.com>
Project-URL: Source, https://github.com/jaraco/jaraco.text
Classifier: Development Status :: 5 - Production/Stable
Classifier: Intended Audience :: Developers
Classifier: License :: OSI Approved :: MIT License
Classifier: Programming Language :: Python :: 3
Classifier: Programming Language :: Python :: 3 :: Only
Requires-Python: >=3.8
License-File: LICENSE
Requires-Dist: jaraco.functools
Requires-Dist: jaraco.context>=4.1
Requires-Dist: importlib_resources; python_version < "3.9"
Requires-Dist: autocommand
Requires-Dist: more_itertools
Provides-Extra: test
Requires-Dist: pytest!=8.1.*,>=6; extra == "test"
Requires-Dist: pytest-checkdocs>=2.4; extra == "test"
Requires-Dist: pytest-cov; extra == "test"
Requires-Dist: pytest-mypy; extra == "test"
Requires-Dist: pytest-enabler>=2.2; extra == "test"
Requires-Dist: pytest-ruff>=0.2.1; sys_platform != "cygwin" and extra == "test"
Requires-Dist: pathlib2; python_version < "3.10" and extra == "test"
Provides-Extra: doc
Requires-Dist: sphinx>=3.5; extra == "doc"
Requires-Dist: jaraco.packaging>=9.3; extra == "doc"
Requires-Dist: rst.linker>=1.9; extra == "doc"
Requires-Dist: furo; extra == "doc"
Requires-Dist: sphinx-lint; extra == "doc"
Requires-Dist: jaraco.tidelift>=1.4; extra == "doc"
Provides-Extra: inflect
Requires-Dist: inflect; extra == "inflect"
